Workbook

Sheet Dashboard
A1: July 12-31, 2026 Revenue Sprint - Restrategized
A2: Goal: collect $2,000 by July 31 without betting the whole month on one cold channel.
A4: Metric | B4: Value | C4: How it is calculated / why it matters
A5: Revenue target | B5: 2000 | C5: Cash collected by Jul 31, 2026.
A6: Cash collected | B6: =SUM('Daily Metrics'!L:L) | C6: Update Daily Metrics every night.
A7: Remaining | B7: =B5-B6 | C7: Amount still required.
A8: Weighted pipeline | B8: =SUM('Pipeline Tracker'!N:N) | C8: Amount x probability for active deals.
A9: Replies / conversations | B9: =SUM('Daily Metrics'!F:F) | C9: Daily market feedback, not vanity outreach.
A10: Calls booked | B10: =SUM('Daily Metrics'!G:G) | C10: A real buying process starts here.
A11: Proposals sent | B11: =SUM('Daily Metrics'!I:I) | C11: Formal paid opportunity count.
A12: Paid audits sold | B12: =SUM('Daily Metrics'!J:J) | C12: Fastest smaller ticket.
A13: Sprint deposits | B13: =SUM('Daily Metrics'!K:K) | C13: Best path to full $2k.
A14: Task completion | B14: =IFERROR(COUNTIF('Daily Plan'!L:L,"Done")/COUNTIF('Daily Plan'!A:A,">0"),0) | C14: Execution check.
A16: Priority | B16: Track | C16: July Role | D16: Reasoning | E16: Offer
A17: 1 | B17: Warm network tech/ops gigs | C17: Primary cash path | D17: Highest short-term trust. Use people who know your work to reach founders/operators with manual workflow pain. | E17: $300-$500 audit or $1.5k-$2.5k sprint
A18: 2 | B18: Agency/operator automation | C18: Secondary cash path | D18: Agencies understand onboarding/reporting pain and can justify a fixed-scope workflow sprint quickly. | E18: $400 audit or $1.5k-$2k implementation
A19: 3 | B19: Western swim/sports academy | C19: Niche beachhead test | D19: Good fit with SwimBuddz proof, but cold trust is slower. Test hard for 5 days before overcommitting. | E19: $300-$500 Lead-to-Enrollment Leak Audit
A20: 4 | B20: StrokeLab digital product | C20: Proof and lead magnet | D20: Useful for authority and swim niche credibility, but not the best standalone July cash bet. | E20: Free/low-ticket proof asset
A21: 5 | B21: Corporate wellness / local SwimBuddz | C21: Backup channel | D21: Useful where relationships already exist. Do not let it distract from cash conversations. | E21: Corporate intro or cohort conversion
A24: Gate Date | B24: Required Signal | C24: Decision
A25: 2026-07-16 | B25: Swim/sports has 5 replies OR 2 calls OR 1 paid-audit interest | C25: If missed, reduce swim cold outreach to 20 percent and shift to warm/agency.
A26: 2026-07-20 | B26: At least 1 proposal sent OR $300+ paid audit sold | C26: If missed, make direct high-trust asks and offer smaller paid audit.
A27: 2026-07-24 | B27: $500+ collected OR signed sprint/proposal | C27: If missed, stop broad outreach and pursue only strongest 10 leads.
A28: 2026-07-28 | B28: $1,000+ collected or committed | C28: Push implementation deposits, urgent audit delivery, and referrals.

Sheet Daily Plan
A1: Day-to-Day Execution Plan: Jul 12-31, 2026
A2: Use Status daily. Apps Script can create reminders from rows where Create Reminder is TRUE.
A4: Date | B4: Day | C4: Start Time | D4: End Time | E4: Track | F4: Priority | G4: Task | H4: Action Steps | I4: Expected Output | J4: Success Metric | K4: Prospect / Asset | L4: Status | M4: Create Reminder | N4: Reminder Lead Mins | O4: Calendar Event ID | P4: Notes
A5: 46215 | B5: Sun | C5: 08:30 | D5: 09:15 | E5: Strategy | F5: P0 | G5: Lock July revenue rule | H5: Write the rule: $2k by Jul 31 from either one implementation sprint or 4-5 paid audits. Confirm the three tracks and the gate dates. | I5: One clear July rule | J5: Rule written and visible on Dashboard | K5: Dashboard | L5: Not Started | M5: TRUE | N5: 15
A6: 46215 | B6: Sun | C6: 11:30 | D6: 13:00 | E6: Pipeline | F6: P0 | G6: Seed 40-prospect universe | H6: Add 10 warm founder/operator contacts, 15 swim/sports academy prospects, 10 agency/operator prospects, and 5 local backup buyers. | I6: 40 pipeline rows | J6: 40 prospects added with pain clues | K6: Pipeline Tracker | L6: Not Started | M6: TRUE | N6: 15
A7: 46215 | B7: Sun | C7: 16:00 | D7: 17:30 | E7: Offers | F7: P0 | G7: Prepare offer assets | H7: Finalize warm ask, swim-school lead-to-enrollment audit, agency onboarding/reporting audit, follow-up, and paid-audit close scripts. | I7: Outreach pack ready | J7: 5 reusable scripts ready | K7: Offers & Templates | L7: Not Started | M7: TRUE | N7: 15
A8: 46215 | B8: Sun | C8: 19:30 | D8: 21:00 | E8: Warm Network | F8: P0 | G8: Send first direct asks | H8: Send 10 warm/referral messages and 5 personalized swim/sports academy messages. Record every send in Pipeline Tracker. | I8: 15 messages sent | J8: 15 logged touches | K8: Warm contacts + swim prospects | L8: Not Started | M8: TRUE | N8: 15
A9: 46215 | B9: Sun | C9: 21:00 | D9: 21:20 | E9: Admin/Review | F9: P0 | G9: Update daily metrics | H9: Record messages sent, replies, calls booked, cash collected, and one market signal. | I9: Day 1 metrics | J9: Daily Metrics row updated | K9: Daily Metrics | L9: Not Started | M9: TRUE | N9: 15
A10: 46216 | B10: Mon | C10: 07:30 | D10: 08:00 | E10: Admin/Review | F10: P0 | G10: Morning score and reply triage | H10: Check WhatsApp, LinkedIn, email, and calendar. Pick top 10 people to move today. | I10: Priority list | J10: Top 10 next actions selected | K10: Daily Metrics | L10: Not Started | M10: TRUE | N10: 15
A11: 46216 | B11: Mon | C11: 12:30 | D11: 13:15 | E11: Warm Network | F11: P0 | G11: Send 15 warm/referral asks | H11: Ask for one founder/operator intro or one painful workflow worth auditing. Keep it specific and direct. | I11: 15 warm messages | J11: 15 sent and logged | K11: Warm contacts | L11: Not Started | M11: TRUE | N11: 15
A12: 46216 | B12: Mon | C12: 15:30 | D12: 17:00 | E12: Swim/Sports Niche | F12: P0 | G12: Record 2 Loom teardown drafts | H12: Pick 2 swim/sports prospects with visible inquiry/trial/booking leaks. Record short teardown or write detailed notes if Loom is not ready. | I12: 2 teardown assets | J12: 2 personalized observations ready | K12: Swim prospects | L12: Not Started | M12: TRUE | N12: 15
A13: 46216 | B13: Mon | C13: 19:30 | D13: 21:00 | E13: Agency/Operator | F13: P1 | G13: Send 10 agency/operator messages | H13: Target agencies or operators with onboarding, reporting, intake, or dashboard pain. Offer a 48h workflow audit. | I13: 10 messages sent | J13: 10 sent and logged | K13: Agency prospects | L13: Not Started | M13: TRUE | N13: 15
A14: 46217 | B14: Tue | C14: 07:30 | D14: 08:15 | E14: Proof | F14: P0 | G14: Draft SwimBuddz proof one-pager | H14: Summarize SwimBuddz OS, cohort registration, club subscription, payment/referral asks, and workflow complexity as proof of execution. | I14: Proof one-pager draft | J14: One page drafted | K14: SwimBuddz proof | L14: Not Started | M14: TRUE | N14: 15
A15: 46217 | B15: Tue | C15: 12:30 | D15: 13:15 | E15: Warm Network | F15: P0 | G15: Follow up and ask for calls | H15: Follow up all replies and ask for 15-minute calls. Send 10 additional warm asks if reply volume is low. | I15: Calls requested | J15: 3 calls requested/booked | K15: Warm contacts | L15: Not Started | M15: TRUE | N15: 15
A16: 46217 | B16: Tue | C16: 15:30 | D16: 17:30 | E16: Calls/Discovery | F16: P0 | G16: Discovery/call block | H16: Hold booked calls or send call invitations with 2 time windows. Push toward paid audit when pain is concrete. | I16: Calls advanced | J16: 2 calls booked or held | K16: Pipeline Tracker | L16: Not Started | M16: TRUE | N16: 15
... A96: 46234 | B96: Fri | C96: 21:00 | D96: 21:20 | E96: Admin/Review | F96: P0 | G96: Update metrics and market signal | H96: Record sends, replies, calls, proposals, cash collected, and what the market said back. | I96: Metrics updated | J96: Daily Metrics row updated | K96: Daily Metrics | L96: Not Started | M96: TRUE | N96: 15

Sheet Daily Metrics
A1: Daily Metrics
A2: Answer every night: what did the market say back?
A4: Date | B4: Day | C4: Warm Messages | D4: Swim/Academy Messages | E4: Agency/Operator Messages | F4: Replies | G4: Calls Booked | H4: Calls Held | I4: Proposals Sent | J4: Paid Audits Sold | K4: Sprint Deposits | L4: Cash Collected | M4: Market Signal | N4: Next Adjustment | O4: Done?
A5: 46215 | B5: Sun | O5: FALSE
A6: 46216 | B6: Mon | O6: FALSE
A7: 46217 | B7: Tue | O7: FALSE
A8: 46218 | B8: Wed | O8: FALSE
A9: 46219 | B9: Thu | O9: FALSE
A10: 46220 | B10: Fri | O10: FALSE
A11: 46221 | B11: Sat | O11: FALSE
A12: 46222 | B12: Sun | O12: FALSE
A13: 46223 | B13: Mon | O13: FALSE
A14: 46224 | B14: Tue | O14: FALSE
A15: 46225 | B15: Wed | O15: FALSE
A16: 46226 | B16: Thu | O16: FALSE
... A24: 46234 | B24: Fri | O24: FALSE

Sheet Pipeline Tracker
A1: Pipeline Tracker
A2: Do not count outreach as progress until it creates replies, calls, proposals, cash, or useful market feedback.
A4: Date Added | B4: Track | C4: Segment | D4: Market | E4: Prospect | F4: Contact | G4: URL / LinkedIn | H4: Pain Clue | I4: Current Tools | J4: Offer | K4: Stage | L4: Amount | M4: Probability | N4: Weighted Value | O4: Next Action | P4: Next Action Date | Q4: Last Touch | R4: Notes
A5: 46215 | B5: Warm Network | C5: Founder/operator contact | D5: Your network | E5: Warm Contact 1 | H5: Knows your work or can intro you to founders/operators. | J5: Referral Ask | K5: Not Contacted | L5: 0 | M5: 0.2 | N5: =L5*M5 | O5: Replace with actual name and send direct ask. | P5: 46215 | R5: Starter seed. Verify contact before sending.
A6: 46215 | B6: Warm Network | C6: Former colleague/client | D6: Your network | E6: Warm Contact 2 | H6: Has seen your technical ability or execution. | J6: Referral Ask | K6: Not Contacted | L6: 0 | M6: 0.2 | N6: =L6*M6 | O6: Replace with actual name and send direct ask. | P6: 46215 | R6: Starter seed. Verify contact before sending.
A7: 46215 | B7: Warm Network | C7: Founder friend | D7: Your network | E7: Warm Contact 3 | H7: Can name one founder/operator with manual workflow pain. | J7: Referral Ask | K7: Not Contacted | L7: 0 | M7: 0.2 | N7: =L7*M7 | O7: Replace with actual name and send direct ask. | P7: 46215 | R7: Starter seed. Verify contact before sending.
A8: 46215 | B8: Warm Network | C8: SwimBuddz member/contact | D8: Your network | E8: Warm Contact 4 | H8: Trust path through SwimBuddz/community. | J8: Referral Ask | K8: Not Contacted | L8: 0 | M8: 0.15 | N8: =L8*M8 | O8: Replace with actual name and ask for intro. | P8: 46215 | R8: Starter seed. Verify contact before sending.
A9: 46215 | B9: Warm Network | C9: Open-source/tech contact | D9: Your network | E9: Warm Contact 5 | H9: Can refer agency/founder/operator contacts. | J9: Referral Ask | K9: Not Contacted | L9: 0 | M9: 0.15 | N9: =L9*M9 | O9: Replace with actual name and ask for intro. | P9: 46215 | R9: Starter seed. Verify contact before sending.
A10: 46215 | B10: Warm Network | C10: Previous school/Unilag contact | D10: Your network | E10: Warm Contact 6 | H10: AI/ML credibility path. | J10: Referral Ask | K10: Not Contacted | L10: 0 | M10: 0.15 | N10: =L10*M10 | O10: Replace with actual name and ask for intro. | P10: 46215 | R10: Starter seed. Verify contact before sending.
A11: 46215 | B11: Warm Network | C11: Rolf/expert path | D11: Your network | E11: Warm Contact 7 | H11: Can advise or introduce higher-quality buyers. | J11: Referral Ask | K11: Not Contacted | L11: 0 | M11: 0.15 | N11: =L11*M11 | O11: Replace with actual name and ask for intro. | P11: 46215 | R11: Starter seed. Verify contact before sending.
A12: 46215 | B12: Warm Network | C12: Community founder | D12: Your network | E12: Warm Contact 8 | H12: Likely knows people running small operations. | J12: Referral Ask | K12: Not Contacted | L12: 0 | M12: 0.15 | N12: =L12*M12 | O12: Replace with actual name and ask for intro. | P12: 46215 | R12: Starter seed. Verify contact before sending.
A13: 46215 | B13: Warm Network | C13: Past project stakeholder | D13: Your network | E13: Warm Contact 9 | H13: Can validate backend/automation execution. | J13: Referral Ask | K13: Not Contacted | L13: 0 | M13: 0.15 | N13: =L13*M13 | O13: Replace with actual name and ask for intro. | P13: 46215 | R13: Starter seed. Verify contact before sending.
A14: 46215 | B14: Warm Network | C14: Trusted friend with founder network | D14: Your network | E14: Warm Contact 10 | H14: Can connect you quickly without cold trust problem. | J14: Referral Ask | K14: Not Contacted | L14: 0 | M14: 0.15 | N14: =L14*M14 | O14: Replace with actual name and ask for intro. | P14: 46215 | R14: Starter seed. Verify contact before sending.
A15: 46215 | B15: Swim/Sports Niche | C15: Swim school | D15: US | E15: Goldfish Swim School | G15: https://goldfishswimschool.com/ | H15: Assessment, registration portal, class levels, multiple locations, make-up lessons. | J15: Paid Audit | K15: Not Contacted | L15: 400 | M15: 0.1 | N15: =L15*M15 | O15: Target a local franchise owner/operator, not only HQ. | P15: 46215 | R15: Starter seed. Verify contact before sending.
A16: 46215 | B16: Swim/Sports Niche | C16: Swim school | D16: US | E16: British Swim School | G16: https://britishswimschool.com/ | H16: Location finder, swim assessment, programs for children/adults/adaptive aquatics. | J16: Paid Audit | K16: Not Contacted | L16: 400 | M16: 0.1 | N16: =L16*M16 | O16: Target a local owner/operator. | P16: 46215 | R16: Starter seed. Verify contact before sending.
A17: 46215 | B17: Swim/Sports Niche | C17: Swim school | D17: US | E17: Aqua-Tots Swim Schools | G17: https://www.aqua-tots.com/ | H17: Enrollment, levels, franchise locations, likely parent follow-up workflow. | J17: Paid Audit | K17: Not Contacted | L17: 400 | M17: 0.1 | N17: =L17*M17 | O17: Target regional/franchise operator. | P17: 46215 | R17: Starter seed. Verify contact before sending.
A18: 46215 | B18: Swim/Sports Niche | C18: Swim school | D18: US | E18: SafeSplash Swim School | G18: https://www.safesplash.com/ | H18: Kids/adult lessons, locations, booking/enrollment flow. | J18: Paid Audit | K18: Not Contacted | L18: 400 | M18: 0.1 | N18: =L18*M18 | O18: Target location-level operator. | P18: 46215 | R18: Starter seed. Verify contact before sending.
A19: 46215 | B19: Swim/Sports Niche | C19: Swim school | D19: US | E19: Big Blue Swim School | G19: https://bigblueswimschool.com/ | H19: Class enrollment, parent-facing scheduling, multi-location operation. | J19: Paid Audit | K19: Not Contacted | L19: 400 | M19: 0.08 | N19: =L19*M19 | O19: Likely has mature systems; use as research or local franchise target. | P19: 46215 | R19: Starter seed. Verify contact before sending.
A20: 46215 | B20: Swim/Sports Niche | C20: Swim school | D20: US | E20: Emler Swim School | G20: https://emlerswimschool.com/ | H20: Class levels, enrollment, parent/student progression. | J20: Paid Audit | K20: Not Contacted | L20: 400 | M20: 0.08 | N20: =L20*M20 | O20: Look for individual location decision maker. | P20: 46215 | R20: Starter seed. Verify contact before sending.
A21: 46215 | B21: Swim/Sports Niche | C21: Swim school | D21: US | E21: Foss Swim School | G21: https://www.fossswimschool.com/ | H21: Enrollment, class levels, multi-location operations. | J21: Paid Audit | K21: Not Contacted | L21: 400 | M21: 0.08 | N21: =L21*M21 | O21: Research local operator before messaging. | P21: 46215 | R21: Starter seed. Verify contact before sending.
A22: 46215 | B22: Swim/Sports Niche | C22: Swim school | D22: US | E22: Bear Paddle Swim School | G22: https://bearpaddle.com/ | H22: Lesson enrollment and progression flow. | J22: Paid Audit | K22: Not Contacted | L22: 400 | M22: 0.08 | N22: =L22*M22 | O22: Research local/franchise contact. | P22: 46215 | R22: Starter seed. Verify contact before sending.
A23: 46215 | B23: Swim/Sports Niche | C23: Private swim lessons | D23: US/Canada | E23: Sunsational Swim School | G23: https://www.sunsationalswimschool.com/ | H23: Private lesson inquiry, matching, scheduling, instructor/customer coordination. | J23: Paid Audit | K23: Not Contacted | L23: 400 | M23: 0.1 | N23: =L23*M23 | O23: Lead matching workflow may be a strong angle. | P23: 46215 | R23: Starter seed. Verify contact before sending.
A24: 46215 | B24: Swim/Sports Niche | C24: Private swim lessons | D24: US/Canada | E24: AquaMobile Swim School | G24: https://aquamobileswim.com/ | H24: At-home lesson booking, instructor matching, payment/follow-up flow. | J24: Paid Audit | K24: Not Contacted | L24: 400 | M24: 0.1 | N24: =L24*M24 | O24: Lead-to-instructor matching workflow may be relevant. | P24: 46215 | R24: Starter seed. Verify contact before sending.
A25: 46215 | B25: Swim/Sports Niche | C25: Swim analysis/coaching | D25: US | E25: SwimLabs | G25: https://www.swimlabs.com/ | H25: Video analysis, lessons, locations, assessment/booking workflow. | J25: Paid Audit | K25: Not Contacted | L25: 400 | M25: 0.08 | N25: =L25*M25 | O25: Good StrokeLab proof comparison. | P25: 46215 | R25: Starter seed. Verify contact before sending.
A26: 46215 | B26: Swim/Sports Niche | C26: Swim school | D26: Australia | E26: Carlile Swimming | G26: https://www.carlile.com.au/ | H26: Learn-to-swim program, levels, enrollment, multiple centers. | J26: Paid Audit | K26: Not Contacted | L26: 400 | M26: 0.08 | N26: =L26*M26 | O26: May be too mature; use as research or local contact. | P26: 46215 | R26: Starter seed. Verify contact before sending.
... A44: 46215 | B44: Corporate Wellness | C44: Fintech/company | D44: Nigeria | E44: Cowrywise | G44: https://cowrywise.com/ | H44: Corporate wellness/community angle; only pursue through warm intro. | J44: Corporate Intro | K44: Not Contacted | L44: 500 | M44: 0.05 | N44: =L44*M44 | O44: Find warm intro first. | P44: 46215 | R44: Starter seed. Verify contact before sending.
N45: =L45*M45
N46: =L46*M46
N47: =L47*M47
N48: =L48*M48
N49: =L49*M49
N50: =L50*M50
N51: =L51*M51
N52: =L52*M52
N53: =L53*M53
N54: =L54*M54
N55: =L55*M55
N56: =L56*M56
... N64: =L64*M64

Sheet Starter Prospects
A1: Starter 40 Prospects / Slots
A2: Replace the 10 warm placeholders with real people. Public cold prospects still need owner/operator contact research before messaging.
A4: Track | B4: Segment | C4: Market | D4: Prospect | E4: Contact | F4: URL / LinkedIn | G4: Pain Clue | H4: Offer | I4: Amount | J4: Probability | K4: Next Action | L4: Stage
A5: Warm Network | B5: Founder/operator contact | C5: Your network | D5: Warm Contact 1 | G5: Knows your work or can intro you to founders/operators. | H5: Referral Ask | I5: 0 | J5: 0.2 | K5: Replace with actual name and send direct ask. | L5: Not Contacted
A6: Warm Network | B6: Former colleague/client | C6: Your network | D6: Warm Contact 2 | G6: Has seen your technical ability or execution. | H6: Referral Ask | I6: 0 | J6: 0.2 | K6: Replace with actual name and send direct ask. | L6: Not Contacted
A7: Warm Network | B7: Founder friend | C7: Your network | D7: Warm Contact 3 | G7: Can name one founder/operator with manual workflow pain. | H7: Referral Ask | I7: 0 | J7: 0.2 | K7: Replace with actual name and send direct ask. | L7: Not Contacted
A8: Warm Network | B8: SwimBuddz member/contact | C8: Your network | D8: Warm Contact 4 | G8: Trust path through SwimBuddz/community. | H8: Referral Ask | I8: 0 | J8: 0.15 | K8: Replace with actual name and ask for intro. | L8: Not Contacted
A9: Warm Network | B9: Open-source/tech contact | C9: Your network | D9: Warm Contact 5 | G9: Can refer agency/founder/operator contacts. | H9: Referral Ask | I9: 0 | J9: 0.15 | K9: Replace with actual name and ask for intro. | L9: Not Contacted
A10: Warm Network | B10: Previous school/Unilag contact | C10: Your network | D10: Warm Contact 6 | G10: AI/ML credibility path. | H10: Referral Ask | I10: 0 | J10: 0.15 | K10: Replace with actual name and ask for intro. | L10: Not Contacted
A11: Warm Network | B11: Rolf/expert path | C11: Your network | D11: Warm Contact 7 | G11: Can advise or introduce higher-quality buyers. | H11: Referral Ask | I11: 0 | J11: 0.15 | K11: Replace with actual name and ask for intro. | L11: Not Contacted
A12: Warm Network | B12: Community founder | C12: Your network | D12: Warm Contact 8 | G12: Likely knows people running small operations. | H12: Referral Ask | I12: 0 | J12: 0.15 | K12: Replace with actual name and ask for intro. | L12: Not Contacted
A13: Warm Network | B13: Past project stakeholder | C13: Your network | D13: Warm Contact 9 | G13: Can validate backend/automation execution. | H13: Referral Ask | I13: 0 | J13: 0.15 | K13: Replace with actual name and ask for intro. | L13: Not Contacted
A14: Warm Network | B14: Trusted friend with founder network | C14: Your network | D14: Warm Contact 10 | G14: Can connect you quickly without cold trust problem. | H14: Referral Ask | I14: 0 | J14: 0.15 | K14: Replace with actual name and ask for intro. | L14: Not Contacted
A15: Swim/Sports Niche | B15: Swim school | C15: US | D15: Goldfish Swim School | F15: https://goldfishswimschool.com/ | G15: Assessment, registration portal, class levels, multiple locations, make-up lessons. | H15: Paid Audit | I15: 400 | J15: 0.1 | K15: Target a local franchise owner/operator, not only HQ. | L15: Not Contacted
A16: Swim/Sports Niche | B16: Swim school | C16: US | D16: British Swim School | F16: https://britishswimschool.com/ | G16: Location finder, swim assessment, programs for children/adults/adaptive aquatics. | H16: Paid Audit | I16: 400 | J16: 0.1 | K16: Target a local owner/operator. | L16: Not Contacted
A17: Swim/Sports Niche | B17: Swim school | C17: US | D17: Aqua-Tots Swim Schools | F17: https://www.aqua-tots.com/ | G17: Enrollment, levels, franchise locations, likely parent follow-up workflow. | H17: Paid Audit | I17: 400 | J17: 0.1 | K17: Target regional/franchise operator. | L17: Not Contacted
A18: Swim/Sports Niche | B18: Swim school | C18: US | D18: SafeSplash Swim School | F18: https://www.safesplash.com/ | G18: Kids/adult lessons, locations, booking/enrollment flow. | H18: Paid Audit | I18: 400 | J18: 0.1 | K18: Target location-level operator. | L18: Not Contacted
A19: Swim/Sports Niche | B19: Swim school | C19: US | D19: Big Blue Swim School | F19: https://bigblueswimschool.com/ | G19: Class enrollment, parent-facing scheduling, multi-location operation. | H19: Paid Audit | I19: 400 | J19: 0.08 | K19: Likely has mature systems; use as research or local franchise target. | L19: Not Contacted
A20: Swim/Sports Niche | B20: Swim school | C20: US | D20: Emler Swim School | F20: https://emlerswimschool.com/ | G20: Class levels, enrollment, parent/student progression. | H20: Paid Audit | I20: 400 | J20: 0.08 | K20: Look for individual location decision maker. | L20: Not Contacted
A21: Swim/Sports Niche | B21: Swim school | C21: US | D21: Foss Swim School | F21: https://www.fossswimschool.com/ | G21: Enrollment, class levels, multi-location operations. | H21: Paid Audit | I21: 400 | J21: 0.08 | K21: Research local operator before messaging. | L21: Not Contacted
A22: Swim/Sports Niche | B22: Swim school | C22: US | D22: Bear Paddle Swim School | F22: https://bearpaddle.com/ | G22: Lesson enrollment and progression flow. | H22: Paid Audit | I22: 400 | J22: 0.08 | K22: Research local/franchise contact. | L22: Not Contacted
A23: Swim/Sports Niche | B23: Private swim lessons | C23: US/Canada | D23: Sunsational Swim School | F23: https://www.sunsationalswimschool.com/ | G23: Private lesson inquiry, matching, scheduling, instructor/customer coordination. | H23: Paid Audit | I23: 400 | J23: 0.1 | K23: Lead matching workflow may be a strong angle. | L23: Not Contacted
A24: Swim/Sports Niche | B24: Private swim lessons | C24: US/Canada | D24: AquaMobile Swim School | F24: https://aquamobileswim.com/ | G24: At-home lesson booking, instructor matching, payment/follow-up flow. | H24: Paid Audit | I24: 400 | J24: 0.1 | K24: Lead-to-instructor matching workflow may be relevant. | L24: Not Contacted
A25: Swim/Sports Niche | B25: Swim analysis/coaching | C25: US | D25: SwimLabs | F25: https://www.swimlabs.com/ | G25: Video analysis, lessons, locations, assessment/booking workflow. | H25: Paid Audit | I25: 400 | J25: 0.08 | K25: Good StrokeLab proof comparison. | L25: Not Contacted
A26: Swim/Sports Niche | B26: Swim school | C26: Australia | D26: Carlile Swimming | F26: https://www.carlile.com.au/ | G26: Learn-to-swim program, levels, enrollment, multiple centers. | H26: Paid Audit | I26: 400 | J26: 0.08 | K26: May be too mature; use as research or local contact. | L26: Not Contacted
... A44: Corporate Wellness | B44: Fintech/company | C44: Nigeria | D44: Cowrywise | F44: https://cowrywise.com/ | G44: Corporate wellness/community angle; only pursue through warm intro. | H44: Corporate Intro | I44: 500 | J44: 0.05 | K44: Find warm intro first. | L44: Not Contacted

Sheet Prospect Criteria
A1: Prospect Criteria
A2: Use this to decide who belongs in the first 40 prospects.
A4: Quota | B4: Segment | C4: Ideal Buyer | D4: Pain Clues | E4: Where To Find | F4: First Offer | G4: Disqualifiers | H4: July Priority
A5: 10 | B5: Warm founder/operator contacts | C5: People who already know your ability or can introduce you to operators. | D5: Manual admin, missed follow-ups, data scattered across tools, repeated reporting. | E5: LinkedIn, WhatsApp, former projects, founders in your circle. | F5: Referral ask or paid workflow audit. | G5: No trust path, no operational pain, no budget owner. | H5: Highest
A6: 15 | B6: Western swim schools / sports academies | C6: Owners or operators of swim schools, adult swim programs, triathlon swim coaches, kids sports academies. | D6: Inquiry form, trial/assessment booking, class levels, waitlist, waivers, multiple locations, payment follow-up. | E6: USA Swimming, USMS, Google Maps, local directories, LinkedIn. | F6: Lead-to-Enrollment Leak Audit. | G6: No clear owner/contact, no booking/enrollment flow, tiny volunteer-only club. | H6: Market test
A7: 10 | B7: Agencies / small operators | C7: Small agencies, implementation shops, consultants, SaaS operators, or service teams. | D7: Client onboarding, intake docs, reporting, dashboards, recurring status updates, messy handoff. | E7: LinkedIn, founder communities, agency directories, warm intros. | F7: Client Onboarding/Reporting Workflow Audit. | G7: Pure content agencies with no ops pain, no decision maker, no budget. | H7: High
A8: 5 | B8: Backup local/corporate SwimBuddz | C8: HR/People/Ops teams, community leaders, wellness decision makers, clubs. | D8: Employee wellness, beginner adult swimming, safety, community, team bonding. | E8: Warm network, LinkedIn, local companies, past SwimBuddz contacts. | F8: Corporate swim/wellness intro call. | G8: No warm path, no wellness budget, long procurement. | H8: Backup

Sheet Offers & Templates
A1: Offers & Templates
A2: Use direct, concrete offers. Do not sell generic AI automation.
A4: Track | B4: Asset | C4: Copy / Script | D4: Use When | E4: Notes
A5: Strategy | B5: July rule | C5: By July 31, collect $2k from either one $1.5k-$2.5k implementation sprint or 4-5 $300-$500 paid audits. Primary cash path is warm-network tech/ops gigs. Swim/sports academy is a 5-day niche test, not the only bet. | D5: Dashboard / daily reminder | E5: This prevents overcommitting to a slow cold market.
A6: Warm Network | B6: Direct ask | C6: Hey [Name], quick ask. I am looking to close 1-2 fixed-scope workflow automation projects before July 31. I am strongest at AI/backend systems, integrations, internal tools, dashboards, and operational workflows. Do you know any founder/operator losing time or leads because a manual process is messy? I can do either a 48h paid audit or a 10-day implementation sprint. | D6: People who know your work | E6: Highest short-term probability because trust already exists.
A7: Swim/Sports Niche | B7: Cold opener | C7: Hi [Name], I run SwimBuddz and noticed [specific clue from their booking/enrollment flow]. A lot of swim schools lose leads between inquiry, assessment, trial, class placement, payment, and follow-up. I am testing a 48h Lead-to-Enrollment Leak Audit: Loom teardown, flow map, quick fixes, and an implementation plan. Would it be useful if I sent one specific observation from your current flow? | D7: Owners/operators with visible lead flow | E7: Ask permission first if there is no warm connection.
A8: Agency/Operator | B8: Cold opener | C8: Hi [Name], I noticed your team handles [client/service type]. Agencies often lose time in client onboarding and reporting: intake docs, status updates, dashboards, recurring reports, and follow-ups. I build fixed-scope backend/automation workflows. Open to me sending one specific observation about a workflow you could tighten? | D8: Small agencies/operators | E8: This is the fastest adjacent niche if swim replies are weak.
A9: Closing | B9: Paid audit close | C9: Based on what you described, I would not start with a full build. I would do a 48h workflow audit first: map the current flow, identify leaks, propose quick wins, and give you the implementation plan. It is $400 and I credit it toward the sprint if we build. Want me to do that this week? | D9: After a call or strong reply | E9: Do not leave conversations at 'let me know'.
A10: Closing | B10: Sprint close | C10: The sprint would focus on one workflow end-to-end: [workflow]. Deliverables: intake/booking flow, integrations, reminders, payment/status tracking, simple dashboard, error handling, and handover notes. Timeline: 10 business days. Price: $1.5k-$2.5k depending on scope. To reserve the week, I take a 50 percent deposit. | D10: When audit/call reveals concrete pain | E10: Keep scope narrow; one workflow only.
A11: Follow-up | B11: Follow-up 1 | C11: Quick follow-up on this. Is lead follow-up / onboarding / reporting currently a real problem for you, or is it already handled well enough? | D11: 2 days after no reply | E11: Forces useful market feedback.
A12: Follow-up | B12: Referral follow-up | C12: No worries if not you. Is there one founder/operator you think this would be more relevant for? | D12: Warm network non-buyer | E12: Converts non-buyers into intros.

Sheet Gate Logic
A1: Gate Logic
A2: Use the market response to decide. Do not argue with weak signals.
A4: Date | B4: Question | C4: Green Signal | D4: Red Signal | E4: Action If Green | F4: Action If Red
A5: 2026-07-16 | B5: Is swim/sports academy a real July cash path? | C5: 5 replies, 2 calls, or 1 paid-audit interest. | D5: Fewer than 3 replies and no call momentum. | E5: Keep swim at 40 percent of outreach and continue Loom teardowns. | F5: Reduce swim to 20 percent; shift to warm network and agency/operator.
A6: 2026-07-20 | B6: Is any channel producing buyer conversations? | C6: 1 proposal or $300+ paid audit sold. | D6: Only polite replies and no paid ask accepted. | E6: Push proposals and sprint deposits. | F6: Make direct high-trust asks; lower friction with $300 audit.
A7: 2026-07-24 | B7: Is cash collection on track? | C7: $500+ collected or signed sprint. | D7: No committed money. | E7: Deliver fast and ask for referrals/deposit. | F7: Stop cold experiments; work only strongest 10 leads.
A8: 2026-07-28 | B8: Can $2k close by Jul 31? | C8: $1k+ collected/committed and at least one sprint in negotiation. | D8: No committed buyer. | E8: Push sprint deposit and paid audit bundle. | F8: Use immediate cash alternatives: direct contract work, referrals, local corporate intro.

Sheet Reminder Config
A1: Reminder Config
A2: Paste Apps Script Code into Extensions > Apps Script, then run syncPlanReminders.
A4: Key | B4: Value | C4: Description
A5: Calendar ID | B5: primary | C5: Use primary calendar unless you paste a specific calendar ID.
A6: Event Prefix | B6: Revenue Sprint | C6: Prefix added to calendar events.
A7: Max Events Per Run | B7: 20 | C7: Keeps Apps Script under event creation limits. Run again later for remaining rows.
A8: Dry Run | B8: FALSE | C8: Set TRUE to test logging without creating events.
A9: Timezone | B9: Africa/Lagos | C9: Your local planning timezone.
A10: Start Date | B10: 2026-07-12 | C10: First date in this workbook.
A11: End Date | B11: 2026-07-31 | C11: Last date in this workbook.

Sheet Apps Script Code
A1: Apps Script Code
A2: Copy the code below into Apps Script for idempotent calendar reminders.
A4: const PLAN_SHEET_NAME = 'Daily Plan'; const CONFIG_SHEET_NAME = 'Reminder Config'; function syncPlanReminders() { const ss = SpreadsheetApp.getActive(); const plan = ss.getSheetByName(PLAN_SHEET_NAME); const config = readConfig_(); const calendar = getCalendar_(config); const maxEvents = Number(config['Max Events Per Run'] || 20); const dryRun = String(config['Dry Run'] || 'FALSE').toUpperCase() === 'TRUE'; const prefix = config['Event Prefix'] || 'Revenue Sprint'; const values = plan.getDataRange().getValues(); const h = headerMap_(values[3]); let changed = 0; for (let r = 4; r < values.length; r++) { if (changed >= maxEvents) break; const row = values[r]; if (!row[h['Date']] || String(row[h['Create Reminder']]).toUpperCase() !== 'TRUE') continue; const status = String(row[h['Status']] || '').trim(); if (['Done', 'Skipped'].includes(status)) continue; const start = parseTime_(row[h['Date']], row[h['Start Time']]); const end = parseTime_(row[h['Date']], row[h['End Time']]); if (!start || !end || end <= start) continue; const title = `${prefix}: ${row[h['Task']]}`; const description = eventDescription_(row, h); const eventIdCol = h['Calendar Event ID'] + 1; let eventId = row[h['Calendar Event ID']]; let event = eventId ? calendar.getEventById(eventId) : null; if (dryRun) { Logger.log(`[DRY RUN] ${title} ${start} - ${end}`); continue; } if (event) { event.setTitle(title); event.setTime(start, end); event.setDescription(description); resetReminder_(event, row[h['Reminder Lead Mins']]); } else { event = calendar.createEvent(title, start, end, { description }); resetReminder_(event, row[h['Reminder Lead Mins']]); plan.getRange(r + 1, eventIdCol).setValue(event.getId()); } changed++; Utilities.sleep(250); } Logger.log(`Processed ${changed} reminders. If you need more, run syncPlanReminders again after a few minutes.`); } function clearCalendarEventIdsOnly() { const ss = SpreadsheetApp.getActive(); const plan = ss.getSheetByName(PLAN_SHEET_NAME); const values = plan.getDataRange().getValues(); const h = headerMap_(values[3]); plan.getRange(5, h['Calendar Event ID'] + 1, values.length - 4, 1).clearContent(); } function readConfig_() { const sheet = SpreadsheetApp.getActive().getSheetByName(CONFIG_SHEET_NAME); const rows = sheet.getDataRange().getValues(); const config = {}; rows.forEach(row => { if (row[0]) config[String(row[0]).trim()] = row[1]; }); return config; } function getCalendar_(config) { const id = config['Calendar ID']; if (id && id !== 'primary') return CalendarApp.getCalendarById(id); return CalendarApp.getDefaultCalendar(); } function headerMap_(headerRow) { const h = {}; headerRow.forEach((name, idx) => { if (name) h[String(name).trim()] = idx; }); return h; } function parseTime_(dateValue, timeText) { const d = new Date(dateValue); const parts = String(timeText).trim().split(':').map(Number); d.setHours(parts[0] || 0, parts[1] || 0, 0, 0); return d; } function eventDescription_(row, h) { return [ `Track: ${row[h['Track']]}`, `Priority: ${row[h['Priority']]}`, '', 'Action steps:', row[h['Action Steps']], '', `Expected output: ${row[h['Expected Output']]}`, `Success metric: ${row[h['Success Metric']]}`, `Asset/prospect: ${row[h['Prospect / Asset']]}`, '', `Sheet status: ${row[h['Status']]}` ].join('\n'); } function resetReminder_(event, leadMins) { event.removeAllReminders(); const mins = Number(leadMins || 15); event.addPopupReminder(mins); }

Sheet Source Notes
A1: Source Notes
A2: Research basis for the strategy. These links should be rechecked before a larger campaign.
A4: Source | B4: Link | C4: What It Supports | D4: Planning Implication | E4: Reliability
A5: USA Swimming | B5: https://www.usaswimming.org/find-a-team | C5: Large organized swim team ecosystem and directories. | D5: There are many swim-related organizations to target, but club/team is not the same as paid school/operator. | E5: Official
A6: U.S. Masters Swimming | B6: https://www.usms.org/clubs | C6: Adult swim club/program ecosystem. | D6: Adult swim and triathlon-related programs are a relevant adjacent audience. | E6: Official
A7: Jackrabbit Class | B7: https://www.jackrabbitclass.com/ | C7: Youth activity businesses already buy registration, scheduling, enrollment, billing, and engagement software. | D7: Customers pay for operations tools, but there are strong incumbents. Sell implementation around the current stack, not a generic OS. | E7: Vendor
A8: iClassPro | B8: https://www.iclasspro.com/ | C8: Class/camp registration, payments, customer portal, and activity-center management. | D8: Competition is real. The wedge must be a specific leak audit and implementation, not 'software for swim schools'. | E8: Vendor
A9: Uplifter | B9: https://www.uplifterinc.com/ | C9: Sports/activity software for registration, payments, waitlists, communications, forms, and reporting. | D9: Lead-to-enrollment and admin workflows are real pains, but many buyers already have a platform. | E9: Vendor
A10: Amilia | B10: https://www.amilia.com/ | C10: Recreation/YMCA software positioning around registration, membership, operations, and admin time savings. | D10: Operational time savings and enrollment capacity are business outcomes buyers understand. | E10: Vendor
A11: AgencyAnalytics | B11: https://agencyanalytics.com/ | C11: Agencies buy reporting/dashboard automation. | D11: Agency onboarding/reporting is a credible adjacent niche and may close faster than cold swim schools. | E11: Vendor

Sheet Lookups
A1: Lookups
A2: Dropdown source values.
A4: Statuses | B4: Tracks | C4: Stages | D4: Priorities | E4: Offers
A5: Not Started | B5: Warm Network | C5: Not Contacted | D5: P0 | E5: Paid Audit
A6: In Progress | B6: Agency/Operator | C6: Messaged | D6: P1 | E6: Implementation Sprint
A7: Waiting | B7: Swim/Sports Niche | C7: Replied | D7: P2 | E7: Referral Ask
A8: Done | B8: Corporate Wellness | C8: Call Booked | E8: Corporate Intro
A9: Skipped | B9: StrokeLab | C9: Call Held | E9: Digital Product
B10: Admin/Review | C10: Proposal Sent | E10: Other
B11: Strategy | C11: Paid Audit
B12: Proof | C12: Sprint Won
B13: Closing | C13: Lost
B14: Delivery/Closing | C14: Nurture
B15: Other
